odoo/addons/product_pricelist_direct_print_xlsx/README.rst
odoo/addons/product_pricelist_direct_print_xlsx/__init__.py
odoo/addons/product_pricelist_direct_print_xlsx/__manifest__.py
odoo/addons/product_pricelist_direct_print_xlsx/i18n/es.po
odoo/addons/product_pricelist_direct_print_xlsx/i18n/fr.po
odoo/addons/product_pricelist_direct_print_xlsx/i18n/it.po
odoo/addons/product_pricelist_direct_print_xlsx/i18n/product_pricelist_direct_print_xlsx.pot
odoo/addons/product_pricelist_direct_print_xlsx/i18n/tr.po
odoo/addons/product_pricelist_direct_print_xlsx/readme/CONTRIBUTORS.md
odoo/addons/product_pricelist_direct_print_xlsx/readme/DESCRIPTION.md
odoo/addons/product_pricelist_direct_print_xlsx/report/__init__.py
odoo/addons/product_pricelist_direct_print_xlsx/report/product_pricelist_xlsx.py
odoo/addons/product_pricelist_direct_print_xlsx/report/product_pricelist_xlsx.xml
odoo/addons/product_pricelist_direct_print_xlsx/security/ir.model.access.csv
odoo/addons/product_pricelist_direct_print_xlsx/static/description/icon.png
odoo/addons/product_pricelist_direct_print_xlsx/static/description/index.html
odoo/addons/product_pricelist_direct_print_xlsx/tests/__init__.py
odoo/addons/product_pricelist_direct_print_xlsx/tests/test_product_pricelist_direct_print_xlsx.py
odoo/addons/product_pricelist_direct_print_xlsx/wizards/__init__.py
odoo/addons/product_pricelist_direct_print_xlsx/wizards/product_pricelist_print.py
odoo/addons/product_pricelist_direct_print_xlsx/wizards/product_pricelist_print_view.xml
odoo_addon_product_pricelist_direct_print_xlsx-18.0.1.0.2.dist-info/METADATA
odoo_addon_product_pricelist_direct_print_xlsx-18.0.1.0.2.dist-info/WHEEL
odoo_addon_product_pricelist_direct_print_xlsx-18.0.1.0.2.dist-info/top_level.txt
odoo_addon_product_pricelist_direct_print_xlsx-18.0.1.0.2.dist-info/RECORD
